{
  "version": "negation_cues.v2.rules_army",
  "negation_cues": [
    "no",
    "not",
    "never",
    "dont",
    "don't",
    "do not",
    "does not",
    "did not",
    "isn't",
    "is not",
    "aren't",
    "are not",
    "wasn't",
    "was not",
    "without",
    "exclude",
    "skip",
    "not looking for",
    "not interested in",
    "do not need",
    "don't need",
    "no need for",
    "anything but",
    "except",
    "not now"
  ],
  "hedge_cues": [
    "maybe",
    "might",
    "possibly",
    "thinking about",
    "considering",
    "not sure",
    "probably",
    "could be",
    "may add",
    "later",
    "eventually",
    "exploring",
    "comparing",
    "if possible",
    "preferably",
    "tentative"
  ],
  "counterfactual_cues": [
    "if i",
    "if you",
    "if we",
    "would you",
    "could you",
    "might you",
    "hypothetically",
    "suppose",
    "assuming",
    "if i signed",
    "if i paid",
    "if i started today",
    "if budget were no issue",
    "pretend",
    "imagine"
  ],
  "scope_terminators": [
    ".",
    "?",
    "!",
    ";",
    " but ",
    " however ",
    " instead ",
    " rather ",
    " although ",
    " except ",
    " unless "
  ],
  "backward_scope_patterns": [
    "\\b(?P<subject>quote|pricing|timeline|agreement|contract|NDA|payment)\\s+(is|are|was|were)\\s+not\\s+(?P<predicate>finalized|approved|ready|confirmed|included)\\b"
  ]
}